neurapolis_common/__init__.py
neurapolis_common/config.py
neurapolis_common/models/__init__.py
neurapolis_common/models/agenda_item.py
neurapolis_common/models/body.py
neurapolis_common/models/consultation.py
neurapolis_common/models/db_node_dict.py
neurapolis_common/models/file.py
neurapolis_common/models/file_chunk.py
neurapolis_common/models/file_section.py
neurapolis_common/models/legislative_term.py
neurapolis_common/models/location.py
neurapolis_common/models/meeting.py
neurapolis_common/models/membership.py
neurapolis_common/models/organization.py
neurapolis_common/models/paper.py
neurapolis_common/models/person.py
neurapolis_common/models/retriever_llm_xml_field.py
neurapolis_common/models/retriever_state.py
neurapolis_common/models/ris_api_dto.py
neurapolis_common/models/system.py
neurapolis_common/services/__init__.py
neurapolis_common/services/db_session_builder.py
neurapolis_common/services/embeddings.py
neurapolis_common-0.1.19.dist-info/METADATA
neurapolis_common-0.1.19.dist-info/WHEEL
neurapolis_common-0.1.19.dist-info/RECORD
